{
	"credit": "Made with Blockbench",
	"textures": {
		"1": "stand/custom/breathing_style/insect/skin"
	},
	"elements": [
		{
			"name": "right_leg",
			"from": [8, -0.5, 6],
			"to": [12, 11.5, 10],
			"faces": {
				"north": {"uv": [1, 5, 2, 8], "texture": "#1"},
				"east": {"uv": [0, 5, 1, 8], "texture": "#1"},
				"south": {"uv": [3, 5, 4, 8], "texture": "#1"},
				"west": {"uv": [2, 5, 3, 8], "texture": "#1"},
				"up": {"uv": [2, 5, 1, 4], "texture": "#1"},
				"down": {"uv": [3, 4, 2, 5], "texture": "#1"}
			}
		},
		{
			"name": "right_leg_2nd_layer",
			"from": [7.5, -1, 5.5],
			"to": [12.5, 12, 10.5],
			"faces": {
				"north": {"uv": [1, 9, 2, 12], "texture": "#1"},
				"east": {"uv": [0, 9, 1, 12], "texture": "#1"},
				"south": {"uv": [3, 9, 4, 12], "texture": "#1"},
				"west": {"uv": [2, 9, 3, 12], "texture": "#1"},
				"up": {"uv": [2, 9, 1, 8], "texture": "#1"},
				"down": {"uv": [3, 8, 2, 9], "texture": "#1"}
			}
		}
	],
	"display": {
		"head": {
			"translation": [-3, -10, 0],
			"scale": [1.5, 1.5, 1.5]
		}
	},
	"groups": [
		{
			"name": "steve",
			"origin": [8, 8, 8],
			"color": 0,
			"children": [0, 1]
		}
	]
}